thunder_ase/__init__.py
thunder_ase/fireball.py
thunder_ase/optimize.py
thunder_ase/utils/__init__.py
thunder_ase/utils/basis_set.py
thunder_ase/utils/mwfn.py
thunder_ase/utils/shell_dict.py
thunder_ase-0.9.5.dist-info/METADATA
thunder_ase-0.9.5.dist-info/WHEEL
thunder_ase-0.9.5.dist-info/entry_points.txt
thunder_ase-0.9.5.dist-info/top_level.txt
thunder_ase-0.9.5.dist-info/RECORD
