Metadata-Version: 2.4
Name: thunder-ase
Version: 0.9.5
Summary: ASE calculator interface for FIREBALL code
Author-email: PJ Ren <openrpj@gmail.com>
Project-URL: Homepage, https://github.com/thunder-dft/thunder-ase
Project-URL: Bug Tracker, https://github.com/thunder-dft/thunder-ase/issues
Classifier: Programming Language :: Python :: 3
Classifier: License :: OSI Approved :: MIT License
Classifier: Operating System :: OS Independent
Requires-Python: >=3.7
